music_embedding/__init__.py
music_embedding/embedder.py
music_embedding/interval.py
music_embedding-1.1.2.dist-info/LICENSE
music_embedding-1.1.2.dist-info/METADATA
music_embedding-1.1.2.dist-info/WHEEL
music_embedding-1.1.2.dist-info/top_level.txt
music_embedding-1.1.2.dist-info/RECORD
