Metadata-Version: 2.1
Name: music_embedding
Version: 1.1.2
Summary: A package for representing music data based on music theory
Home-page: https://github.com/PooyaHekmati
Download-URL: https://github.com/PooyaHekmati/music_embedding/archive/v1.1.2.tar.gz
Author: Pooya Hekmati
Author-email: s.pooyahekmati.a@gmail.com
License: MIT
Project-URL: Documentation, https://pooyahekmati.github.io/music_embedding/
Keywords: music,interval,pianoroll,embedding,knowledge representation
Classifier: Development Status :: 5 - Production/Stable
Classifier: Intended Audience :: Developers
Classifier: Topic :: Software Development :: Build Tools
Classifier: License :: OSI Approved :: MIT License
Classifier: Programming Language :: Python :: 3
Requires-Python: >=3.10
License-File: LICENSE
Requires-Dist: numpy
Provides-Extra: test
Requires-Dist: pytest >=6.0 ; extra == 'test'
Requires-Dist: pytest-cov >=2.0 ; extra == 'test'
